<Properties StartupConfiguration="{05EEAE16-EA89-4465-AC54-C0D905CFD626}|Default">
  <MonoDevelop.Ide.ItemProperties.BinarySearch PreferredExecutionTarget="MonoDevelop.Default" />
  <MonoDevelop.Ide.DebuggingService.PinnedWatches />
  <MonoDevelop.Ide.Workbench ActiveDocument="PrefixSum/Program.cs">
    <Files>
      <File FileName="PrefixSum/Program.cs" Line="25" Column="1" />
    </Files>
    <Pads>
      <Pad Id="ProjectPad">
        <State name="__root__">
          <Node name="MainProjects" expanded="True">
            <Node name="BinarySearch" expanded="True" />
            <Node name="PrefixSum" expanded="True" />
          </Node>
        </State>
      </Pad>
    </Pads>
  </MonoDevelop.Ide.Workbench>
  <MonoDevelop.Ide.DebuggingService.Breakpoints>
    <BreakpointStore />
  </MonoDevelop.Ide.DebuggingService.Breakpoints>
  <MonoDevelop.Ide.ItemProperties.PrefixSum PreferredExecutionTarget="MonoDevelop.Default" />
  <MonoDevelop.Ide.Workspace ActiveConfiguration="Debug" />
  <MultiItemStartupConfigurations />
</Properties>